{"type":"PR","pr":{"number":71,"head":"d9b7fbb628c50b38bdf6d15431cd1aa049bd7217"},"user":"Amanda Almeida Matos","status":"draft","branch":"cms/posts/2020-07-10-regexp","collection":"posts","commitMessage":"Create Posts “2020-07-10-regexp”","title":"Regexp","description":"Aprendendo a utilizar com javascript","objects":{"entry":{"path":"posts/2020-07-10-regexp.md","sha":"1f232436b52aa1120c22b7db34e456f5dc9cadd9"},"files":[{"path":"static/assets/img/Captura de tela de 2020-07-09 23-51-22.png","sha":"dd699127517e17566f46d2c08ca7c2953717b949"},{"path":"static/assets/img/Captura de tela de 2020-07-09 23-40-45.png","sha":"0d43ddb1612eb8db329d6643f3cbbd5cef5d029a"},{"path":"static/assets/img/Captura de tela de 2020-07-09 23-36-45.png","sha":"4cc2cd12395d99b85633771fb58e7e04bcd5a3a7"}]},"timeStamp":"2020-07-10T02:37:13.810Z","version":"1"}